[
    {
        "id": 1,
        "nom": "Menu signature",
        "prix": "20",
        "nb personnes": "1",
        "description": "L'expérience japo-indienne a son paroxisme : faites un voyage en inde et au japon en un seul repas."
    },
    {
        "id": 2,
        "nom": "Menu japonais",
        "prix": "22",
        "nb personnes": "1",
        "description": "L'expérience japonaise complète: du plate au dessert en passant par la boisson."
    },
    {
        "id": 3,
        "nom": "Menu indiens",
        "prix": "22",
        "nb personnes": "1",
        "description": "L'expérience indienne complète: du plate au dessert en passant par la boisson."
    },
    {
        "id": 4,
        "nom": "Coca-Cola",
        "prix": "2,5",
        "allergène": [],
        "image": "../photos/coca.png",
        "description": "Une boisson rafraîchissante et populaire."
    },
    {
        "id": 5,
        "nom": "Ice Tea",
        "prix": "2,5",
        "allergène": [],
        "image": "../photos/icetea.png",
        "description": "Une boisson rafraîchissante à la pêche."
    },
    {
        "id": 6,
        "nom": "Jus de pomme",
        "prix": "2,5",
        "allergène": [],
        "image": "../photos/juspomme.png",
        "description": "Un jus de pomme frais et naturel."
    },
    {
        "id": 7,
        "nom": "Scheweppes",
        "prix": "2,5",
        "allergène": [],
        "image": "../photos/scheweppes.png",
        "description": "Une boisson rafraîchissante aux agrumes."
    },
    {
        "id": 8,
        "nom": "Mogu",
        "prix": "3",
        "allergène": [],
        "image": "../photos/mogu.png",
        "description": "Une boisson traditionnelle à la fraise."
    },
    {
        "id": 9,
        "nom": "Lassi mangue",
        "prix": "4,5",
        "allergène": [],
        "image": "../photos/lassimangue.png",
        "description": "Un lassi rafraîchissant à la mangue."
    },
    {
        "id": 10,
        "nom": "Maki curry",
        "prix": "13,5",
        "allergène": [
            "poisson"
        ],
        "image": "../photos/sushicurry.png",
        "description": "Délicieux assortiment de riz et d'une sauce curry secrète."
    },
    {
        "id": 11,
        "nom": "Samousa boeuf de kobé",
        "prix": "12",
        "allergène": [
            "viande"
        ],
        "image": "../photos/samousa.png",
        "description": "Un samousa composé du boeuf le plus tendre du monde."
    },
    {
        "id": 12,
        "nom": "cheese naan au saké",
        "prix": "11,5",
        "allergène": [],
        "image": "../photos/cheesenaan.png",
        "description": "Un délicieux et tendre cheese naan relevé au saké"
    },
    {
        "id": 13,
        "nom": "Poulet Tandoori mariné au whisky japonais",
        "prix": "13,5",
        "allergène": [
            "viande"
        ],
        "image": "../photos/poulettando.png",
        "description": "Un poulet mariné dans un whisky japonais d'excellence pour une tendresse exceptionnelle."
    },
    {
        "id": 14,
        "nom": "Soupe miso poulet Tikka massala",
        "prix": "12",
        "allergène": [],
        "image": "../photos/soupemiso.png",
        "description": "Une soupe miso composé d'un poulet Tikkaa Massala pour un plat aussi gourmand que léger."
    },
    {
        "id": 15,
        "nom": "brochette yakitori de Ladoo",
        "prix": "11,5",
        "allergène": [
            "viande"
        ],
        "image": "../photos/brochette.png",
        "description": "Une délicieuse brochette de viande de Ladoo grillée à la perfection."
    },
    {
        "id": 16,
        "nom": "Onigiri poulet tiki tikka",
        "prix": "13,5",
        "allergène": [
            "viande"
        ],
        "image": "../photos/onigiri.png",
        "description": "Un onigiri composé d'un poulet assaisonné de tiki tikka."
    },
    {
        "id": 17,
        "nom": "Donburi au curry d'agneau",
        "prix": "12",
        "allergène": [
            "viande"
        ],
        "image": "../photos/donburi.png",
        "description": "Un Donburi composé d'un morceau tendre d'agneau et d'une sauce curry"
    },
    {
        "id": 18,
        "nom": "poulpe au cumin",
        "prix": "11,5",
        "allergène": [
            "poisson"
        ],
        "image": "../photos/poulpe.png",
        "description": "Un tentacule de poulpe épicé au cumin"
    },
    {
        "id": 19,
        "nom": "Tonkatsu",
        "prix": "13,5",
        "allergène": [
            "viande"
        ],
        "image": "../photos/tonkatsu.png",
        "description": "Porc pané et frit accompagné de sauce Worcestershire, ainsi que de chou émincé et du karashi."
    },
    {
        "id": 20,
        "nom": "Ramen",
        "prix": "12",
        "allergène": [
            "viande"
        ],
        "image": "../photos/ramen.png",
        "description": "Ramen au bœuf assaisonné au miso, accompagné de légumes (maïs, algue, pousse de bambou, poireaux)"
    },
    {
        "id": 21,
        "nom": "Katsu Curry",
        "prix": "11,5",
        "allergène": [
            "viande"
        ],
        "image": "../photos/katsu.png",
        "description": "Un morceau de viande de porc pané et frit accompagné d'une délicieuse sauce curry."
    },
    {
        "id": 22,
        "nom": "Chirachi anguille",
        "prix": "13,5",
        "allergène": [
            "poisson"
        ],
        "image": "../photos/chirachi.png",
        "description": "Riz vinaigré recouvert de fines tranches d'anguille grillée."
    },
    {
        "id": 23,
        "nom": "Assortiment de sushi et maki",
        "prix": "12",
        "allergène": [
            "poisson"
        ],
        "image": "../photos/sushi.png",
        "description": "Plateau composé de différents types de sushi et maki."
    },
    {
        "id": 24,
        "nom": "Yakiniku",
        "prix": "11,5",
        "allergène": [
            "viande"
        ],
        "image": "../photos/yakiniku.png",
        "description": "Viande de bœuf grillée à la perfection, accompagnée de légumes et d'une sauce spéciale."
    },
    {
        "id": 25,
        "nom": "Poulet Tikkaa Massala",
        "prix": "13,5",
        "allergène": [
            "viande"
        ],
        "image": "../photos/poulettikka.jpg",
        "description": "Poulet mariné dans une sauce au yaourt et à l'ail, grillé et servi avec du riz et des légumes."
    },
    {
        "id": 26,
        "nom": "Poulet Tandori",
        "prix": "12",
        "allergène": [
            "viande"
        ],
        "image": "../photos/poulettandori.jpg",
        "description": "Poulet mariné dans une sauce au yaourt et à l'ail, grillé et servi avec du riz et des légumes."
    },
    {
        "id": 27,
        "nom": "Dahl",
        "prix": "11,5",
        "allergène": [],
        "image": "../photos/dahl.jpg",
        "description": "Un plat traditionnel à base de lentilles et de légumes, servi avec du riz."
    },
    {
        "id": 28,
        "nom": "Aloo Gobi",
        "prix": "13,5",
        "allergène": [],
        "image": "../photos/aloo.jpg",
        "description": "Pommes de terre et chou-fleur dans une sauce au yaourt et à l'ail."
    },
    {
        "id": 29,
        "nom": "Ladoo",
        "prix": "12",
        "allergène": [],
        "image": "../photos/ladoo.jpg",
        "description": "Douceur indienne à base de sucre et de farine de pois chiches."
    },
    {
        "id": 30,
        "nom": "Raita",
        "prix": "11,5",
        "allergène": [],
        "image": "../photos/raita.jpg",
        "description": "Salade fraîche à base de yaourt et de légumes : concombres, carottes, tomates"
    },
    {
        "id": 31,
        "nom": "Mochis",
        "prix": "5",
        "allergène": [],
        "image": "../photos/mochis.jpg",
        "description": "Doux et moelleux, ces gâteaux japonais sont parfaits pour terminer un repas."
    },
    {
        "id": 32,
        "nom": "Cheesecake",
        "prix": "8,5",
        "allergène": [],
        "image": "../photos/cheesecake.png",
        "description": "Doux et crémeux, ce cheesecake est un dessert incontournable du Japon."
    },
    {
        "id": 33,
        "nom": "Dorayaki",
        "prix": "4,5",
        "allergène": [],
        "image": "../photos/dorayaki.png",
        "description": "Un dessert japonais composé de pancakes fourrés avec une garniture de pâte de haricot rouge."
    },
    {
        "id": 34,
        "nom": "Kulfi",
        "prix": "6,5",
        "allergène": [],
        "image": "../photos/kulfi.png",
        "description": "Un dessert indien traditionnel à base de lait concentré et de sucre."
    },
    {
        "id": 35,
        "nom": "Gulab Jamun",
        "prix": "5,5",
        "allergène": [],
        "image": "../photos/gulab-jamun.png",
        "description": "Douceur indienne à base de sucre et de farine de pois chiches."
    },
    {
        "id": 36,
        "nom": "Jalebi",
        "prix": "4,5",
        "allergène": [],
        "image": "../photos/jalebi.png",
        "description": "Douceur indienne à base de sucre et de farine de pois chiches."
    }
]